{"symbol": "QQQ", "name": "Invesco QQQ Trust", "sector": "N/A", "industry": "N/A", "country": "N/A", "exchange": "NGM", "currency": "USD", "market_cap": 184340316160, "pe_ratio": 30.05428, "forward_pe": null, "pb_ratio": 1.3107158, "dividend_yield": 0.56, "beta": null, "description": "To maintain the correspondence between the composition and weights of the securities in the trust (the \"securities\") and the stocks in the NASDAQ-100 Index\u00ae, the adviser adjusts the securities from time to time to conform to periodic changes in the identity and/or relative weights of index securities. The composition and weighting of the securities portion of a portfolio deposit are also adjusted to conform to changes in the index.", "website": "N/A", "employees": null, "logo_url": null, "type": "ETF", "last_updated": "2025-03-29"}